proof_business_api/__init__.py
proof_business_api/client.py
proof_business_api/documents.py
proof_business_api/records.py
proof_business_api/resource.py
proof_business_api/transactions.py
proof_business_api/types.py
proof_business_api/watch.py
proof_business_api/webhooks.py
proof_business_api-0.4.0.dist-info/METADATA
proof_business_api-0.4.0.dist-info/WHEEL
proof_business_api-0.4.0.dist-info/entry_points.txt
proof_business_api-0.4.0.dist-info/RECORD
